setup.py
earth/__init__.py
earth/_version.py
earth.egg-info/PKG-INFO
earth.egg-info/SOURCES.txt
earth.egg-info/dependency_links.txt
earth.egg-info/requires.txt
earth.egg-info/top_level.txt