Metadata-Version: 1.0
Name: earth
Version: 0.0.1
Summary: All of it
Home-page: UNKNOWN
Author: Nathan Longbotham
Author-email: nathan@descarteslabs.com
License: UNKNOWN
Platform: UNKNOWN
